LICENSE
MANIFEST.in
README.rst
requirements.txt
setup.py
src/django_context_logging.py
src/django_context_logging.egg-info/PKG-INFO
src/django_context_logging.egg-info/SOURCES.txt
src/django_context_logging.egg-info/dependency_links.txt
src/django_context_logging.egg-info/not-zip-safe
src/django_context_logging.egg-info/requires.txt
src/django_context_logging.egg-info/top_level.txt