Metadata-Version: 1.1
Name: django-context-logging
Version: 1.2.1
Summary: Library for adding request context to log records
Home-page: https://github.com/lorehov/django_context_logging
Author: Lev Orekhov
Author-email: lev.orekhov@gmail.com
License: BSD
Keywords: django context logging
Platform: UNKNOWN
Classifier: Intended Audience :: Developers
Classifier: Programming Language :: Python
Classifier: Programming Language :: Python :: 2
Classifier: Programming Language :: Python :: 3
Classifier: Operating System :: OS Independent
Classifier: Topic :: Software Development :: Libraries
Classifier: Topic :: Software Development :: Libraries :: Python Modules
